pipdownload/__init__.py
pipdownload/__main__.py
pipdownload/cli.py
pipdownload/exceptions.py
pipdownload/settings.py
pipdownload/utils.py
tests/__init__.py
tests/conftest.py
tests/test_cli.py
tests/test_utils.py
pip_download-0.4.2.dist-info/LICENSE-MIT
pip_download-0.4.2.dist-info/METADATA
pip_download-0.4.2.dist-info/WHEEL
pip_download-0.4.2.dist-info/entry_points.txt
pip_download-0.4.2.dist-info/top_level.txt
pip_download-0.4.2.dist-info/RECORD
