Metadata-Version: 2.1
Name: pip-download
Version: 0.4.2
Summary: A wrapper for pip download in offline scenario.
Home-page: https://github.com/youngquan/pip-download
Author: youngquan
Author-email: youngquan@qq.com
Maintainer: youngquan
Maintainer-email: youngquan@qq.com
License: MIT/Apache-2.0
Keywords: pip download,cross platform,offline packages
Platform: UNKNOWN
Classifier: Development Status :: 4 - Beta
Classifier: Intended Audience :: Developers
Classifier: License :: OSI Approved :: MIT License
Classifier: License :: OSI Approved :: Apache Software License
Classifier: Natural Language :: English
Classifier: Operating System :: OS Independent
Classifier: Programming Language :: Python :: 3.6
Classifier: Programming Language :: Python :: 3.7
Classifier: Programming Language :: Python :: 3.8
Classifier: Programming Language :: Python :: 3.9
Classifier: Programming Language :: Python :: Implementation :: CPython
Requires-Dist: click
Requires-Dist: requests
Requires-Dist: cachecontrol
Requires-Dist: packaging
Requires-Dist: retrying
Requires-Dist: pip-api
Requires-Dist: tzlocal
Requires-Dist: pip
Requires-Dist: appdirs
Provides-Extra: dev
Requires-Dist: isort ; extra == 'dev'
Requires-Dist: autoflake ; extra == 'dev'
Requires-Dist: black ; extra == 'dev'
